loggerplusplus/__init__.py
loggerplusplus/api.py
loggerplusplus/decorators.py
loggerplusplus/logger_class.py
loggerplusplus/parser.py
loggerplusplus/proxy.py
loggerplusplus/registry.py
loggerplusplus/runtime.py
loggerplusplus/formats/__init__.py
loggerplusplus/formats/base.py
loggerplusplus/formats/classic.py
loggerplusplus/formats/debug.py
loggerplusplus/formats/minimal.py
loggerplusplus/formats/ops.py
loggerplusplus/formats/short.py
loggerplusplus-1.0.1.dist-info/licenses/LICENSE
loggerplusplus-1.0.1.dist-info/METADATA
loggerplusplus-1.0.1.dist-info/WHEEL
loggerplusplus-1.0.1.dist-info/top_level.txt
loggerplusplus-1.0.1.dist-info/RECORD
