Metadata-Version: 2.4
Name: loggerplusplus
Version: 1.0.1
Summary: LoggerPlusPlus is an enhanced Python logging module with colorized output, customizable themes, improved multi-logger management, and optimized display for better readability. Built on top of Loguru, it adds a set of features that make logging faster and more convenient to use.
License:                     GNU GENERAL PUBLIC LICENSE
Keywords: logging,loguru,logger,structured-logging,colorized
Classifier: Development Status :: 5 - Production/Stable
Classifier: Intended Audience :: Developers
Classifier: Topic :: System :: Logging
Classifier: License :: OSI Approved :: GNU General Public License v3 (GPLv3)
Classifier: Programming Language :: Python
Classifier: Programming Language :: Python :: 3
Classifier: Programming Language :: Python :: 3 :: Only
Classifier: Programming Language :: Python :: 3.8
Classifier: Programming Language :: Python :: 3.9
Classifier: Programming Language :: Python :: 3.10
Classifier: Programming Language :: Python :: 3.11
Classifier: Programming Language :: Python :: 3.12
Requires-Python: >=3.8
License-File: LICENSE
Requires-Dist: loguru>=0.7
Requires-Dist: colorama>=0.4.6
Requires-Dist: loguru>=0.7.3
Requires-Dist: setuptools>=78.1.1
Requires-Dist: wheel>=0.45.1
Requires-Dist: win32_setctime>=1.2.0
Dynamic: license-file
